README.rst
setup.py
salary_timetracker.egg-info/PKG-INFO
salary_timetracker.egg-info/SOURCES.txt
salary_timetracker.egg-info/dependency_links.txt
salary_timetracker.egg-info/entry_points.txt
salary_timetracker.egg-info/requires.txt
salary_timetracker.egg-info/top_level.txt
timetracker/__init__.py
timetracker/db_router.py
timetracker/timetracker.py