Metadata-Version: 1.1
Name: salary-timetracker
Version: 0.6
Summary: A simple and easy timetracker for loging working hours and automatic wage calculation.
Home-page: http://github.com/dalay/salary-timetracker
Author: Alexandr Jurow
Author-email: pythonwayru@gmail.com
License: GPL
Download-URL: https://github.com/dalay/salary-timetracker/archive/v0.6.tar.gz
Keywords: timetracker,salary,freelance
Platform: UNKNOWN
Classifier: Development Status :: 4 - Beta
Classifier: Environment :: Console
Classifier: Intended Audience :: Developers
Classifier: License :: OSI Approved :: GNU General Public License (GPL)
Classifier: Operating System :: POSIX :: Linux
Classifier: Programming Language :: Python
Classifier: Programming Language :: Python :: 3.4
Classifier: Programming Language :: Python :: 3.5
Classifier: Programming Language :: Python :: 3.6
Classifier: Topic :: Utilities
